agende/__init__.py
agende/agende.py
agende-0.2.2.dist-info/LICENSE
agende-0.2.2.dist-info/METADATA
agende-0.2.2.dist-info/WHEEL
agende-0.2.2.dist-info/entry_points.txt
agende-0.2.2.dist-info/top_level.txt
agende-0.2.2.dist-info/RECORD
