Metadata-Version: 2.1
Name: agende
Version: 0.2.2
Summary: Agendador automático para o Restaurante Universitário da UFC
Home-page: https://github.com/Pedro-Emanuel/agende
Author: Pedro Emanuel
Author-email: Pedro Emanuel <pedroems.147@gmail.com>
License: MIT License
Project-URL: Homepage, https://github.com/Pedro-Emanuel/agende
Project-URL: Bug Tracker, https://github.com/Pedro-Emanuel/agende/issues
Classifier: Programming Language :: Python :: 3
Classifier: License :: OSI Approved :: MIT License
Classifier: Operating System :: OS Independent
Requires-Python: >=3.7
License-File: LICENSE
Requires-Dist: selenium
Requires-Dist: webdriver-manager
Requires-Dist: getch
